pyope/__init__.py
pyope/errors.py
pyope/hgd.py
pyope/ope.py
pyope/stat.py
pyope/util.py
pyope-0.2.2.dist-info/DESCRIPTION.rst
pyope-0.2.2.dist-info/LICENSE.txt
pyope-0.2.2.dist-info/METADATA
pyope-0.2.2.dist-info/RECORD
pyope-0.2.2.dist-info/WHEEL
pyope-0.2.2.dist-info/metadata.json
pyope-0.2.2.dist-info/top_level.txt
