Metadata-Version: 1.1
Name: pyope
Version: 0.2.2
Summary: Implementation of symmetric order-preserving encryption scheme
Home-page: https://github.com/tonyo/pyope/
Author: Anton Ovchinnikov
Author-email: anton.ovchi2nikov@gmail.com
License: MIT
Platform: UNKNOWN
Classifier: License :: OSI Approved :: MIT License
Classifier: Programming Language :: Python
Classifier: Topic :: Security :: Cryptography
